ucrspawner/__init__.py
ucrspawner/_version.py
ucrspawner/exceptions.py
ucrspawner/mesosslave.py
ucrspawner/ucrspawner.py
ucrspawner/utils.py
ucrspawner/volumenaming.py
ucrspawner/templates/options_form.html
ucrspawner-0.0.9.dist-info/DESCRIPTION.rst
ucrspawner-0.0.9.dist-info/METADATA
ucrspawner-0.0.9.dist-info/RECORD
ucrspawner-0.0.9.dist-info/WHEEL
ucrspawner-0.0.9.dist-info/metadata.json
ucrspawner-0.0.9.dist-info/top_level.txt
