Metadata-Version: 2.0
Name: ucrspawner
Version: 0.0.9
Summary: JupyterHub spawner for Marathon UCR
Home-page: https://github.com/dtaniwaki/ucrspawner
Author: Daisuke Taniwaki
Author-email: daisuketaniwaki@gmail.com
License: MIT
Keywords: JupyterHub Marathon UCR Mesos
Platform: UNKNOWN
Classifier: Development Status :: 3 - Alpha
Classifier: License :: OSI Approved :: MIT License
Classifier: Programming Language :: Python :: 3
Classifier: Framework :: Jupyter
Requires-Python: >=3.3
Requires-Dist: jupyterhub (<1dev,>=0.7)
Requires-Dist: marathon (<1dev,>=0.9)
Provides-Extra: cov
Requires-Dist: coverage (<5dev,>=4.5.0); extra == 'cov'
Provides-Extra: flake8
Requires-Dist: flake8 (<4dev,>=3.5.0); extra == 'flake8'
Requires-Dist: autoflake (<2dev,>=1.1); extra == 'flake8'
Requires-Dist: autopep8 (<2dev,>=1.3); extra == 'flake8'
Requires-Dist: flake8-blind-except (<1dev,>=0.1.1); extra == 'flake8'
Requires-Dist: flake8-import-order (<1dev,>=0.16); extra == 'flake8'
Requires-Dist: flake8-html (<1dev,>=0.4.0); extra == 'flake8'
Provides-Extra: test
Requires-Dist: pytest (<3.3,>=3.0); extra == 'test'
Requires-Dist: pytest-cov (<3dev,>=2.5); extra == 'test'
Requires-Dist: pytest-html (<2dev,>=1.15.2); extra == 'test'
